dkregression/__init__.py
dkregression/dkr.py
dkregression/cross_validation/__init__.py
dkregression/cross_validation/cross_validation.py
dkregression/kernels/__init__.py
dkregression/kernels/rbf.py
dkregression/likelihoods/__init__.py
dkregression/likelihoods/bernoulli.py
dkregression/likelihoods/misc.py
dkregression/likelihoods/multivariate_gaussian.py
dkregression/likelihoods/poisson.py
dkregression/likelihoods/univariate_gaussian.py
dkregression-0.0.6.dist-info/WHEEL
dkregression-0.0.6.dist-info/METADATA
dkregression-0.0.6.dist-info/RECORD
