Metadata-Version: 2.1
Name: dkregression
Version: 0.0.6
Summary: Python package for distributional kernel regression
Author-email: Marc Schlichting <mschl@stanford.edu>
Requires-Python: >=3.9
Requires-Dist: torch>=2.0.0
Requires-Dist: nevergrad>=1.0.2
Requires-Dist: pytest ; extra == "dev"
Requires-Dist: colormath ; extra == "tutorials"
Requires-Dist: airportsdata ; extra == "tutorials"
Requires-Dist: basemap ; extra == "tutorials"
Requires-Dist: matplotlib ; extra == "tutorials"
Requires-Dist: basemap ; extra == "tutorials"
Requires-Dist: requests ; extra == "tutorials"
Requires-Dist: oauthlib ; extra == "tutorials"
Requires-Dist: tqdm ; extra == "tutorials"
Requires-Dist: pandas ; extra == "tutorials"
Provides-Extra: dev
Provides-Extra: tutorials
